imesde-0.5.0.dist-info/METADATA
imesde-0.5.0.dist-info/WHEEL
imesde/__init__.py
imesde/imesde.cpython-313t-aarch64-linux-gnu.so
imesde-0.5.0.dist-info/RECORD
