Metadata-Version: 2.4
Name: imesde
Version: 0.5.0
Summary: Python bindings for imesde engine
Requires-Python: >=3.10
